iambic/__init__.py
iambic/config/__init__.py
iambic/config/dynamic_config.py
iambic/config/utils.py
iambic/config/wizard.py
iambic/core/__init__.py
iambic/core/aio_utils/__init__.py
iambic/core/context.py
iambic/core/detect.py
iambic/core/exceptions.py
iambic/core/git.py
iambic/core/iambic_enum.py
iambic/core/iambic_plugin.py
iambic/core/logger.py
iambic/core/models.py
iambic/core/noq_json.py
iambic/core/parser.py
iambic/core/template_generation.py
iambic/core/utils.py
iambic/lambda/__init__.py
iambic/lambda/app.py
iambic/main.py
iambic/output/__init__.py
iambic/output/filters.py
iambic/output/markdown.py
iambic/output/models.py
iambic/output/templates/github_summary.jinja2
iambic/output/templates/text_file_summary.jinja2
iambic/output/templates/text_screen_summary.jinja2
iambic/output/text.py
iambic/plugins/README.md
iambic/plugins/__init__.py
iambic/plugins/v0_1_0/__init__.py
iambic/plugins/v0_1_0/aws/__init__.py
iambic/plugins/v0_1_0/aws/cloud_formation/__init__.py
iambic/plugins/v0_1_0/aws/cloud_formation/templates/IambicHubRole.yml
iambic/plugins/v0_1_0/aws/cloud_formation/templates/IambicSpokeRole.yml
iambic/plugins/v0_1_0/aws/cloud_formation/templates/IambicSpokeRoleReadOnly.yml
iambic/plugins/v0_1_0/aws/cloud_formation/templates/IdentityRuleDestination.yml
iambic/plugins/v0_1_0/aws/cloud_formation/templates/IdentityRuleForwarder.yml
iambic/plugins/v0_1_0/aws/cloud_formation/templates/iambic_github_app_code_build.yaml
iambic/plugins/v0_1_0/aws/cloud_formation/templates/iambic_github_app_ecr_pull_through.yaml
iambic/plugins/v0_1_0/aws/cloud_formation/templates/iambic_github_app_ecr_repo.yaml
iambic/plugins/v0_1_0/aws/cloud_formation/templates/iambic_github_app_lambda.yaml
iambic/plugins/v0_1_0/aws/cloud_formation/templates/iambic_github_app_roles.yaml
iambic/plugins/v0_1_0/aws/cloud_formation/utils.py
iambic/plugins/v0_1_0/aws/event_bridge/__init__.py
iambic/plugins/v0_1_0/aws/event_bridge/models.py
iambic/plugins/v0_1_0/aws/handlers.py
iambic_core-0.11.97.dist-info/LICENSE.md
iambic_core-0.11.97.dist-info/METADATA
iambic_core-0.11.97.dist-info/WHEEL
iambic_core-0.11.97.dist-info/entry_points.txt
iambic_core-0.11.97.dist-info/RECORD
