Metadata-Version: 2.1
Name: iambic-core
Version: 0.11.97
Summary: IAMbic is a multi-cloud IAM control plane that unifies cloud identity management for AWS, Okta, Azure Active Directory, Google Workspace and more into Git.
License: Apache-2.0
Author: Noq Software
Author-email: hello@noq.dev
Requires-Python: >=3.9,<4.0
Classifier: License :: OSI Approved :: Apache Software License
Classifier: Programming Language :: Python :: 3
Classifier: Programming Language :: Python :: 3.9
Classifier: Programming Language :: Python :: 3.10
Classifier: Programming Language :: Python :: 3.11
Classifier: Programming Language :: Python :: 3.12
Requires-Dist: GitPython (>=3.1.31,<4.0.0)
Requires-Dist: Jinja2 (>=3.1.2,<4.0.0)
Requires-Dist: PyGithub (==1.57)
Requires-Dist: aiofiles (>=23.1.0,<24.0.0)
Requires-Dist: aiohttp (>=3.8.5,<4.0.0)
Requires-Dist: asgiref (>=3.6.0,<4.0.0)
Requires-Dist: asyncache (>=0.3.1,<0.4.0)
Requires-Dist: aws-error-utils (>=2.7.0,<3.0.0)
Requires-Dist: boto3 (>=1.26.95,<2.0.0)
Requires-Dist: click (>=8.1.3,<9.0.0)
Requires-Dist: cryptography (>=41.0.1,<42.0.0)
Requires-Dist: dateparser (>=1.1.7,<2.0.0)
Requires-Dist: deepdiff (>=6.3.0,<7.0.0)
Requires-Dist: dictdiffer (>=0.9.0,<0.10.0)
Requires-Dist: google-api-python-client (>=2.81.0,<3.0.0)
Requires-Dist: google-auth (>=2.16.2,<3.0.0)
Requires-Dist: msal (>=1.21.0,<2.0.0)
Requires-Dist: okta (>=2.9.2,<3.0.0)
Requires-Dist: pydantic (>=1.10.6,<2.0.0)
Requires-Dist: pydantic-factories (>=1.17.2,<2.0.0)
Requires-Dist: pyopenssl (>=23.0.0,<24.0.0)
Requires-Dist: questionary (>=1.10.0,<2.0.0)
Requires-Dist: rich (>=13.3.2,<14.0.0)
Requires-Dist: ruamel.yaml (>=0.17.21,<0.18.0)
Requires-Dist: slack-bolt (>=1.16.4,<2.0.0)
Requires-Dist: stringcase (>=1.2.0,<2.0.0)
Requires-Dist: structlog (>=23.1.0,<24.0.0)
Requires-Dist: tenacity (>=8.2.2,<9.0.0)
Requires-Dist: tomlkit (>=0.11.8,<0.12.0)
Requires-Dist: types-dateparser (>=1.1.4.5,<2.0.0.0)
Requires-Dist: typing-extensions (>=4.6.1,<5.0.0)
Requires-Dist: ujson (>=5.7.0,<6.0.0)
Requires-Dist: xxhash (>=3.2.0,<4.0.0)
